licatools/__init__.py
licatools/_version.py
licatools/eclipse.py
licatools/filters.py
licatools/hamamatsu.py
licatools/metadata.py
licatools/ndfilters.py
licatools/osi.py
licatools/photod.py
licatools/plot.py
licatools/tessw.py
licatools/dbase/__init__.py
licatools/dbase/api/__init__.py
licatools/dbase/api/metadata.py
licatools/dbase/api/model.py
licatools/dbase/cli/__init__.py
licatools/dbase/cli/main.py
licatools/dbase/cli/parser.py
licatools/resources/__init__.py
licatools/resources/global.mplstyle
licatools/resources/multi.mplstyle
licatools/resources/single.mplstyle
licatools/utils/__init__.py
licatools/utils/parser.py
licatools/utils/processing.py
licatools/utils/table.py
licatools/utils/validators.py
licatools/utils/mpl/__init__.py
licatools/utils/mpl/helpers.py
licatools/utils/mpl/plotter/__init__.py
licatools/utils/mpl/plotter/base.py
licatools/utils/mpl/plotter/box.py
licatools/utils/mpl/plotter/element.py
licatools/utils/mpl/plotter/table.py
licatools/utils/mpl/plotter/types.py
licatools-0.3.12.dist-info/licenses/LICENSE
licatools-0.3.12.dist-info/METADATA
licatools-0.3.12.dist-info/WHEEL
licatools-0.3.12.dist-info/entry_points.txt
licatools-0.3.12.dist-info/top_level.txt
licatools-0.3.12.dist-info/RECORD
