Metadata-Version: 2.4
Name: licatools
Version: 0.3.12
Summary: Tools to reduce and plot data from LICA Optical Bench
Author-email: Rafael González <rafael08@ucm.es>, Jaime Zamorano <jzamoran@ucm.es>
Project-URL: Homepage, https://github.com/guaix-ucm/licaplot
Project-URL: Repository, https://github.com/guaix-ucm/licaplot.git
Classifier: Programming Language :: Python :: 3.9
Classifier: Programming Language :: Python :: 3.10
Classifier: Programming Language :: Python :: 3.11
Classifier: Programming Language :: Python :: 3.12
Classifier: Development Status :: 4 - Beta
Classifier: Environment :: Console
Classifier: Intended Audience :: Science/Research
Classifier: Operating System :: OS Independent
Classifier: Topic :: Scientific/Engineering :: Astronomy
Classifier: Topic :: Scientific/Engineering :: Atmospheric Science
Requires-Python: >=3.12
License-File: LICENSE
Requires-Dist: matplotlib>=3.9
Requires-Dist: pyqt5>=5.15
Requires-Dist: astropy>=6.0
Requires-Dist: scipy>=1.13
Requires-Dist: sqlalchemy
Requires-Dist: lica[lab,sqlalchemy]>=1.1.3
Requires-Dist: pytz>=2025.1
Provides-Extra: extras
Requires-Dist: notebook>=7.3; extra == "extras"
Dynamic: license-file
